{"entity":[{"id":1,"sms_id":1,"point_id":1,"isPass":0,"awards":"0","limit":"3,11,1"},{"id":2,"sms_id":1,"point_id":2,"isPass":0,"awards":"","limit":"0"},{"id":3,"sms_id":1,"point_id":3,"isPass":0,"awards":"3,11,10","limit":"0"},{"id":4,"sms_id":1,"point_id":4,"isPass":0,"awards":"3,11,8","limit":"0"},{"id":5,"sms_id":1,"point_id":5,"isPass":0,"awards":"3,11,5","limit":"0"},{"id":6,"sms_id":1,"point_id":6,"isPass":0,"awards":"","limit":"3,9,200"},{"id":7,"sms_id":1,"point_id":7,"isPass":0,"awards":"","limit":"3,8,500"},{"id":8,"sms_id":2,"point_id":8,"isPass":0,"awards":"","limit":"3,11,300"},{"id":9,"sms_id":2,"point_id":9,"isPass":0,"awards":"","limit":"0"},{"id":10,"sms_id":2,"point_id":10,"isPass":0,"awards":"3,11,10","limit":"0"},{"id":11,"sms_id":2,"point_id":11,"isPass":0,"awards":"3,11,8","limit":"0"},{"id":12,"sms_id":2,"point_id":12,"isPass":0,"awards":"3,11,5","limit":"0"},{"id":13,"sms_id":2,"point_id":13,"isPass":0,"awards":"","limit":"3,11,300"},{"id":14,"sms_id":2,"point_id":14,"isPass":0,"awards":"","limit":"3,9,200"},{"id":15,"sms_id":2,"point_id":15,"isPass":0,"awards":"","limit":"3,28,200"},{"id":16,"sms_id":3,"point_id":16,"isPass":0,"awards":"","limit":"0"},{"id":17,"sms_id":3,"point_id":17,"isPass":0,"awards":"","limit":"3,11,300"},{"id":18,"sms_id":3,"point_id":18,"isPass":0,"awards":"","limit":"3,9,500"},{"id":19,"sms_id":4,"point_id":19,"isPass":0,"awards":"","limit":"0"},{"id":20,"sms_id":4,"point_id":20,"isPass":0,"awards":"","limit":"3,11,500"},{"id":21,"sms_id":4,"point_id":21,"isPass":0,"awards":"","limit":"3,9,500"},{"id":22,"sms_id":5,"point_id":22,"isPass":0,"awards":"","limit":"0"},{"id":23,"sms_id":5,"point_id":23,"isPass":0,"awards":"","limit":"3,11,500"},{"id":24,"sms_id":5,"point_id":24,"isPass":0,"awards":"","limit":"3,9,500"},{"id":25,"sms_id":6,"point_id":25,"isPass":0,"awards":"","limit":"0"},{"id":26,"sms_id":6,"point_id":26,"isPass":0,"awards":"","limit":"3,11,500"},{"id":27,"sms_id":6,"point_id":27,"isPass":0,"awards":"","limit":"3,9,500"},{"id":28,"sms_id":7,"point_id":28,"isPass":0,"awards":"","limit":"0"},{"id":29,"sms_id":7,"point_id":29,"isPass":0,"awards":"","limit":"3,11,500"},{"id":30,"sms_id":7,"point_id":30,"isPass":0,"awards":"","limit":"3,9,500"},{"id":31,"sms_id":8,"point_id":31,"isPass":0,"awards":"","limit":"3,9,500"},{"id":32,"sms_id":8,"point_id":32,"isPass":0,"awards":"","limit":"0"},{"id":33,"sms_id":8,"point_id":33,"isPass":0,"awards":"3,9,8","limit":"0"},{"id":34,"sms_id":8,"point_id":34,"isPass":0,"awards":"3,9,10","limit":"0"},{"id":35,"sms_id":8,"point_id":35,"isPass":0,"awards":"3,9,5","limit":"0"},{"id":36,"sms_id":8,"point_id":36,"isPass":0,"awards":"","limit":"3,11,500"},{"id":37,"sms_id":8,"point_id":37,"isPass":0,"awards":"","limit":"3,10,500"},{"id":38,"sms_id":9,"point_id":38,"isPass":0,"awards":"","limit":"3,10,500"},{"id":39,"sms_id":9,"point_id":39,"isPass":0,"awards":"","limit":"0"},{"id":40,"sms_id":9,"point_id":40,"isPass":0,"awards":"3,10,10","limit":"0"},{"id":41,"sms_id":9,"point_id":41,"isPass":0,"awards":"3,10,10","limit":"0"},{"id":42,"sms_id":9,"point_id":42,"isPass":0,"awards":"3,10,10","limit":"0"},{"id":43,"sms_id":9,"point_id":43,"isPass":0,"awards":"","limit":"0"},{"id":44,"sms_id":9,"point_id":44,"isPass":0,"awards":"","limit":"3,11,500"},{"id":45,"sms_id":9,"point_id":45,"isPass":0,"awards":"","limit":"3,9,500"},{"id":46,"sms_id":10,"point_id":46,"isPass":0,"awards":"","limit":"3,28,50"},{"id":47,"sms_id":10,"point_id":47,"isPass":0,"awards":"","limit":"0"},{"id":48,"sms_id":10,"point_id":48,"isPass":0,"awards":"3,28,10","limit":"0"},{"id":49,"sms_id":10,"point_id":49,"isPass":0,"awards":"3,28,10","limit":"0"},{"id":50,"sms_id":10,"point_id":50,"isPass":0,"awards":"3,28,10","limit":"0"},{"id":51,"sms_id":10,"point_id":51,"isPass":0,"awards":"","limit":"3,11,500"},{"id":60,"sms_id":11,"point_id":60,"isPass":0,"awards":"","limit":"3,11,500"},{"id":61,"sms_id":11,"point_id":61,"isPass":0,"awards":"","limit":"0"},{"id":62,"sms_id":11,"point_id":62,"isPass":0,"awards":"3,11,10","limit":"0"},{"id":63,"sms_id":11,"point_id":63,"isPass":0,"awards":"3,11,10","limit":"0"},{"id":64,"sms_id":11,"point_id":64,"isPass":0,"awards":"3,11,5","limit":"0"},{"id":65,"sms_id":11,"point_id":65,"isPass":0,"awards":"","limit":"0"},{"id":66,"sms_id":11,"point_id":66,"isPass":0,"awards":"","limit":"0"},{"id":67,"sms_id":11,"point_id":67,"isPass":0,"awards":"","limit":"0"},{"id":68,"sms_id":11,"point_id":68,"isPass":0,"awards":"","limit":"3,4,500"},{"id":69,"sms_id":11,"point_id":69,"isPass":0,"awards":"","limit":"0"},{"id":70,"sms_id":11,"point_id":70,"isPass":0,"awards":"","limit":"3,10,500"},{"id":71,"sms_id":11,"point_id":71,"isPass":0,"awards":"","limit":"3,9,500"},{"id":72,"sms_id":11,"point_id":72,"isPass":0,"awards":"","limit":"3,8,500"},{"id":73,"sms_id":11,"point_id":73,"isPass":0,"awards":"","limit":"3,14,500"},{"id":74,"sms_id":11,"point_id":74,"isPass":0,"awards":"","limit":"3,12,500"},{"id":75,"sms_id":12,"point_id":75,"isPass":0,"awards":"","limit":"3,11,300"},{"id":76,"sms_id":12,"point_id":76,"isPass":0,"awards":"","limit":"0"},{"id":77,"sms_id":12,"point_id":77,"isPass":0,"awards":"3,11,5","limit":"0"},{"id":78,"sms_id":12,"point_id":78,"isPass":0,"awards":"3,11,8","limit":"0"},{"id":79,"sms_id":12,"point_id":79,"isPass":0,"awards":"3,11,10","limit":"0"},{"id":80,"sms_id":12,"point_id":80,"isPass":0,"awards":"","limit":"0"},{"id":81,"sms_id":12,"point_id":81,"isPass":0,"awards":"","limit":"0"},{"id":82,"sms_id":12,"point_id":82,"isPass":0,"awards":"","limit":"0"},{"id":83,"sms_id":12,"point_id":83,"isPass":0,"awards":"","limit":"3,10,500"},{"id":84,"sms_id":12,"point_id":84,"isPass":0,"awards":"","limit":"3,8,500"},{"id":85,"sms_id":12,"point_id":85,"isPass":0,"awards":"","limit":"3,9,500"},{"id":86,"sms_id":13,"point_id":86,"isPass":0,"awards":"","limit":"3,11,350"},{"id":87,"sms_id":13,"point_id":87,"isPass":0,"awards":"","limit":"0"},{"id":88,"sms_id":13,"point_id":88,"isPass":0,"awards":"3,11,10","limit":"0"},{"id":89,"sms_id":13,"point_id":89,"isPass":0,"awards":"3,11,5","limit":"0"},{"id":90,"sms_id":13,"point_id":90,"isPass":0,"awards":"3,11,8","limit":"0"},{"id":91,"sms_id":13,"point_id":91,"isPass":0,"awards":"","limit":"0"},{"id":92,"sms_id":13,"point_id":92,"isPass":0,"awards":"","limit":"0"},{"id":93,"sms_id":13,"point_id":93,"isPass":0,"awards":"","limit":"0"},{"id":94,"sms_id":13,"point_id":94,"isPass":0,"awards":"","limit":"3,10,500"},{"id":95,"sms_id":13,"point_id":95,"isPass":0,"awards":"","limit":"0"},{"id":96,"sms_id":13,"point_id":96,"isPass":0,"awards":"","limit":"3,4,500"},{"id":97,"sms_id":13,"point_id":97,"isPass":0,"awards":"","limit":"3,8,500"},{"id":98,"sms_id":13,"point_id":98,"isPass":0,"awards":"","limit":"3,9,500"},{"id":99,"sms_id":13,"point_id":99,"isPass":0,"awards":"","limit":"0"},{"id":100,"sms_id":14,"point_id":100,"isPass":0,"awards":"","limit":"3,11,400"},{"id":101,"sms_id":14,"point_id":101,"isPass":0,"awards":"","limit":"0"},{"id":102,"sms_id":14,"point_id":102,"isPass":0,"awards":"3,11,10","limit":"0"},{"id":103,"sms_id":14,"point_id":103,"isPass":0,"awards":"3,11,8","limit":"0"},{"id":104,"sms_id":14,"point_id":104,"isPass":0,"awards":"","limit":"0"},{"id":105,"sms_id":14,"point_id":105,"isPass":0,"awards":"","limit":"0"},{"id":106,"sms_id":14,"point_id":106,"isPass":0,"awards":"","limit":"3,14,500"},{"id":107,"sms_id":14,"point_id":107,"isPass":0,"awards":"","limit":"0"},{"id":108,"sms_id":14,"point_id":108,"isPass":0,"awards":"","limit":"3,12,500"},{"id":109,"sms_id":14,"point_id":109,"isPass":0,"awards":"","limit":"3,8,500"},{"id":110,"sms_id":14,"point_id":110,"isPass":0,"awards":"","limit":"0"},{"id":111,"sms_id":15,"point_id":111,"isPass":0,"awards":"","limit":"3,11,450"},{"id":112,"sms_id":15,"point_id":112,"isPass":0,"awards":"","limit":"0"},{"id":113,"sms_id":15,"point_id":113,"isPass":0,"awards":"3,11,5","limit":"0"},{"id":114,"sms_id":15,"point_id":114,"isPass":0,"awards":"3,11,8","limit":"0"},{"id":115,"sms_id":15,"point_id":115,"isPass":0,"awards":"3,11,10","limit":"0"},{"id":116,"sms_id":15,"point_id":116,"isPass":0,"awards":"","limit":"0"},{"id":117,"sms_id":15,"point_id":117,"isPass":0,"awards":"","limit":"0"},{"id":118,"sms_id":15,"point_id":118,"isPass":0,"awards":"","limit":"0"},{"id":119,"sms_id":15,"point_id":119,"isPass":0,"awards":"","limit":"3,18,500"},{"id":120,"sms_id":15,"point_id":120,"isPass":0,"awards":"","limit":"3,9,500"},{"id":121,"sms_id":15,"point_id":121,"isPass":0,"awards":"","limit":"3,10,500"},{"id":122,"sms_id":15,"point_id":122,"isPass":0,"awards":"","limit":"0"},{"id":123,"sms_id":15,"point_id":123,"isPass":0,"awards":"","limit":"3,1,500"},{"id":124,"sms_id":16,"point_id":124,"isPass":0,"awards":"","limit":"3,11,500"},{"id":125,"sms_id":16,"point_id":125,"isPass":0,"awards":"","limit":"0"},{"id":126,"sms_id":16,"point_id":126,"isPass":0,"awards":"3,11,5","limit":"0"},{"id":127,"sms_id":16,"point_id":127,"isPass":0,"awards":"3,11,7","limit":"0"},{"id":128,"sms_id":16,"point_id":128,"isPass":0,"awards":"3,11,10","limit":"0"},{"id":129,"sms_id":16,"point_id":129,"isPass":0,"awards":"","limit":"0"},{"id":130,"sms_id":16,"point_id":130,"isPass":0,"awards":"","limit":"0"},{"id":131,"sms_id":16,"point_id":131,"isPass":0,"awards":"","limit":"0"},{"id":132,"sms_id":16,"point_id":132,"isPass":0,"awards":"","limit":"3,13,500"},{"id":133,"sms_id":16,"point_id":133,"isPass":0,"awards":"","limit":"3,8,500"},{"id":134,"sms_id":16,"point_id":134,"isPass":0,"awards":"","limit":"0"},{"id":135,"sms_id":16,"point_id":135,"isPass":0,"awards":"","limit":"3,21,500"},{"id":136,"sms_id":16,"point_id":136,"isPass":0,"awards":"","limit":"3,9,500"},{"id":137,"sms_id":16,"point_id":137,"isPass":0,"awards":"","limit":"0"},{"id":138,"sms_id":17,"point_id":138,"isPass":0,"awards":"","limit":"3,11,600"},{"id":139,"sms_id":17,"point_id":139,"isPass":0,"awards":"","limit":"0"},{"id":140,"sms_id":17,"point_id":140,"isPass":0,"awards":"3,11,5","limit":"0"},{"id":141,"sms_id":17,"point_id":141,"isPass":0,"awards":"3,11,8","limit":"0"},{"id":142,"sms_id":17,"point_id":142,"isPass":0,"awards":"3,11,12","limit":"0"},{"id":143,"sms_id":17,"point_id":143,"isPass":0,"awards":"","limit":"0"},{"id":144,"sms_id":17,"point_id":144,"isPass":0,"awards":"","limit":"0"},{"id":145,"sms_id":17,"point_id":145,"isPass":0,"awards":"","limit":"0"},{"id":146,"sms_id":17,"point_id":146,"isPass":0,"awards":"","limit":"3,4,500"},{"id":147,"sms_id":17,"point_id":147,"isPass":0,"awards":"","limit":"3,10,500"},{"id":148,"sms_id":17,"point_id":148,"isPass":0,"awards":"","limit":"3,9,500"},{"id":149,"sms_id":17,"point_id":149,"isPass":0,"awards":"","limit":"3,8,500"},{"id":150,"sms_id":17,"point_id":150,"isPass":0,"awards":"","limit":"3,35,500"},{"id":151,"sms_id":17,"point_id":151,"isPass":0,"awards":"","limit":"0"},{"id":152,"sms_id":18,"point_id":152,"isPass":0,"awards":"","limit":"3,11,800"},{"id":153,"sms_id":18,"point_id":153,"isPass":0,"awards":"","limit":"0"},{"id":154,"sms_id":18,"point_id":154,"isPass":0,"awards":"3,11,10","limit":"0"},{"id":155,"sms_id":18,"point_id":155,"isPass":0,"awards":"3,11,13","limit":"0"},{"id":156,"sms_id":18,"point_id":156,"isPass":0,"awards":"","limit":"0"},{"id":157,"sms_id":18,"point_id":157,"isPass":0,"awards":"","limit":"0"},{"id":158,"sms_id":18,"point_id":158,"isPass":0,"awards":"","limit":"3,19,500"},{"id":159,"sms_id":18,"point_id":159,"isPass":0,"awards":"","limit":"0"},{"id":160,"sms_id":19,"point_id":160,"isPass":0,"awards":"","limit":"3,11,900"},{"id":161,"sms_id":19,"point_id":161,"isPass":0,"awards":"","limit":"0"},{"id":162,"sms_id":19,"point_id":162,"isPass":0,"awards":"3,11,8","limit":"0"},{"id":163,"sms_id":19,"point_id":163,"isPass":0,"awards":"3,11,5","limit":"0"},{"id":164,"sms_id":19,"point_id":164,"isPass":0,"awards":"3,11,10","limit":"0"},{"id":165,"sms_id":19,"point_id":165,"isPass":0,"awards":"","limit":"0"},{"id":166,"sms_id":19,"point_id":166,"isPass":0,"awards":"","limit":"0"},{"id":167,"sms_id":19,"point_id":167,"isPass":0,"awards":"","limit":"0"},{"id":168,"sms_id":19,"point_id":168,"isPass":0,"awards":"","limit":"3,10,500"},{"id":169,"sms_id":19,"point_id":169,"isPass":0,"awards":"","limit":"0"},{"id":170,"sms_id":19,"point_id":170,"isPass":0,"awards":"","limit":"3,8,500"},{"id":171,"sms_id":19,"point_id":171,"isPass":0,"awards":"","limit":"3,14,500"},{"id":172,"sms_id":20,"point_id":172,"isPass":0,"awards":"","limit":"3,11,1000"},{"id":173,"sms_id":20,"point_id":173,"isPass":0,"awards":"","limit":"0"},{"id":174,"sms_id":20,"point_id":174,"isPass":0,"awards":"3,11,5","limit":"0"},{"id":175,"sms_id":20,"point_id":175,"isPass":0,"awards":"3,11,8","limit":"0"},{"id":176,"sms_id":20,"point_id":176,"isPass":0,"awards":"3,11,10","limit":"0"},{"id":177,"sms_id":20,"point_id":177,"isPass":0,"awards":"","limit":"0"},{"id":178,"sms_id":20,"point_id":178,"isPass":0,"awards":"","limit":"0"},{"id":179,"sms_id":20,"point_id":179,"isPass":0,"awards":"","limit":"0"},{"id":180,"sms_id":20,"point_id":180,"isPass":0,"awards":"","limit":"3,10,500"},{"id":181,"sms_id":20,"point_id":181,"isPass":0,"awards":"","limit":"3,3,500"},{"id":182,"sms_id":20,"point_id":182,"isPass":0,"awards":"","limit":"3,12,500"},{"id":183,"sms_id":20,"point_id":183,"isPass":0,"awards":"","limit":"3,8,500"},{"id":184,"sms_id":20,"point_id":184,"isPass":0,"awards":"","limit":"3,9,500"},{"id":185,"sms_id":20,"point_id":185,"isPass":0,"awards":"","limit":"3,14,500"},{"id":190,"sms_id":21,"point_id":190,"isPass":0,"awards":"","limit":"0"},{"id":191,"sms_id":21,"point_id":191,"isPass":0,"awards":"","limit":"0"},{"id":192,"sms_id":21,"point_id":192,"isPass":0,"awards":"3,18,10","limit":"0"},{"id":193,"sms_id":21,"point_id":193,"isPass":0,"awards":"3,18,10","limit":"0"},{"id":194,"sms_id":21,"point_id":194,"isPass":0,"awards":"3,18,10","limit":"0"}]}